nrt_unittest_soft_asserts/__init__.py
nrt_unittest_soft_asserts/soft_asserts.py
nrt_unittest_soft_asserts-1.1.1.data/data/requirements.txt
nrt_unittest_soft_asserts-1.1.1.dist-info/LICENSE.md
nrt_unittest_soft_asserts-1.1.1.dist-info/METADATA
nrt_unittest_soft_asserts-1.1.1.dist-info/WHEEL
nrt_unittest_soft_asserts-1.1.1.dist-info/top_level.txt
nrt_unittest_soft_asserts-1.1.1.dist-info/RECORD
