Metadata-Version: 2.1
Name: nrt-unittest-soft-asserts
Version: 1.1.1
Summary: Soft asserts for unittest
Home-page: https://github.com/etuzon/python-nrt-unittest-soft-asserts
Author: Eyal Tuzon
Author-email: Eyal Tuzon <eyal.tuzon.dev@gmail.com>
Project-URL: Homepage, https://github.com/etuzon/python-nrt-unittest-soft-asserts
Project-URL: Bug Tracker, https://github.com/etuzon/python-nrt-unittest-soft-asserts/issues
Project-URL: documentation, https://github.com/etuzon/python-nrt-unittest-soft-asserts/wiki
Keywords: python,python3,python-3,nrt,unittest,soft,assert,asserts,assertion,assertions,soft-assert,soft-asserts,soft-assertion,soft-assertions,nrt-unittest-soft-asserts
Classifier: Programming Language :: Python :: 3
Classifier: Programming Language :: Python :: 3.9
Classifier: Programming Language :: Python :: 3.10
Classifier: Programming Language :: Python :: 3.11
Classifier: Programming Language :: Python :: 3.12
Classifier: Programming Language :: Python :: 3.13
Classifier: License :: OSI Approved :: MIT License
Classifier: Operating System :: OS Independent
Requires-Python: >=3.9
License-File: LICENSE.md
